my_own_package/__init__.py
Raica_Tiberiu_Paul_Proiect_Hello-0.1.0.dist-info/METADATA
Raica_Tiberiu_Paul_Proiect_Hello-0.1.0.dist-info/WHEEL
Raica_Tiberiu_Paul_Proiect_Hello-0.1.0.dist-info/top_level.txt
Raica_Tiberiu_Paul_Proiect_Hello-0.1.0.dist-info/RECORD
