Metadata-Version: 2.1
Name: Raica-Tiberiu-Paul-Proiect-Hello
Version: 0.1.0
Summary: Says hello to owner
Author: raica Paul
Author-email: Raica_paul@yahoo.com
License: UNKNOWN
Platform: UNKNOWN
